{"records":[{"name":"mquk#0095","time":6287,"link":"#parkour-1601595555577-*#parkour95records Mquk#0095"},{"name":"reses#2305","time":7504,"link":"#parkour-1601602496641-*#parkour0records reses#2305"},{"name":"acoolname#4878","time":9878,"link":"#parkour-1602627708034-*#parkour5records Acoolname#4878"},{"name":"machyato#9373","time":13066,"link":"#parkour-1602636778791-*#parkour0records Acoolname#4878"}],"category":"parkour","img":"https://imgur.com/RbN40r1.png","recordsReversed":[{"name":"quki#0000","time":5834,"link":"#parkour-*#parkour0records quki#0000","breaktime":1646157907814},{"name":"kaanov#9473","time":5900,"link":"#parkour-*#parkour0records Kaanov#9473","timestamp":"2021-01-13T12:59:44.218Z"},{"name":"skypierr#7567","time":5991,"link":"#parkour-*#parkour0records Skypierr#7567","timestamp":"2021-01-28T09:02:08.134Z"},{"name":"acoolname#4878","time":7297,"link":"#parkour-es-#parkour5records Acoolname#4878","timestamp":"2020-12-01T16:33:01.252Z"},{"name":"jeisonequix#0000","time":8433,"link":"#parkour-*#parkour0records Jeisonequix#0000","timestamp":"2020-12-15T18:06:12.617Z"},{"name":"omenox#0000","time":9057,"link":"#parkour-*#parkour00recordsOmenox#0000","timestamp":"2020-12-22T00:55:52.932Z"},{"name":"fredziuuu#0000","time":20751,"link":"#parkour-*#parkour0recordsNair0bi#3975","timestamp":"2020-12-01T13:45:03.970Z"}]}