{"records":[{"name":"dawidektu#0000","time":5655,"link":"#parkour-pl-#parkour0recordsDAwidektu#0000","timestamp":"2020-10-26T11:24:10.290Z"},{"name":"mquk#0095","time":5802,"link":"#parkour-1601741409037-*#parkour95records Mquk#0095"},{"name":"kamal#8011","time":6244,"link":"#parkour-1601689103028-ar-#parkour00records-Kamal#8011"},{"name":"o_ooooooooooooo#3431","time":6443,"link":"#parkour-*#parkour0records O_ooooooooooooo#3431","timestamp":"2020-10-16T22:05:46.981Z"},{"name":"ori#6575","time":6594,"link":"#parkour-1601597932782-*#parkour0records Ori#6575"},{"name":"acoolname#4878","time":8537,"link":"#parkour-1602637247096-*#parkour0records Acoolname#4878"}],"category":"parkour","img":"https://imgur.com/sk8CCSK.png","recordsReversed":[]}