{"records":[{"name":"bitstev#0000","time":7410,"link":"#parkour-1602080534307-*#parkour0records Bitstev#0000"},{"name":"andrew678#0000","time":7647,"link":"#parkour-1601985180614-*#parkour0records Andrew678#0000"},{"name":"pop#0621","time":9421,"link":"#parkour-1601892816585-*#parkour0records0Luqxx#0000"}],"category":"parkour","img":"https://imgur.com/Ce27T5y.png","recordsReversed":[{"name":"brsowl#0000","time":5946,"link":"#parkour-*#parkour0records Brsowl#0000","timestamp":"2020-11-19T11:19:22.980Z"},{"name":"gmctf#0000","time":7092,"link":"#parkour-*#parkour0records Gmctf#0000","timestamp":"2020-11-19T03:51:49.358Z"},{"name":"thefourthone#0000","time":8630,"link":"#parkour-*#parkour4records Thefourthone#0000","timestamp":"2020-11-19T00:28:05.593Z"},{"name":"nineateseven#0000","time":15538,"link":"#parkour-*#parkour4records Nineateseven#0000","timestamp":"2020-11-19T00:10:26.152Z"},{"name":"guisanper#0000","time":18896,"link":"#parkour-*#parkour4records Thefourthone#0000","timestamp":"2020-11-19T00:10:36.433Z"}]}