{"records":[{"name":"canibelles#0000","time":3931,"link":"#parkour-en-#parkour1records Canibelles#0000","timestamp":"2020-10-20T16:33:16.343Z"},{"name":"edudekarly#3398","time":3944,"link":"#parkour-1601819709918-*#parkour0records Syntia#9053"},{"name":"flash01#1465","time":4036,"link":"#parkour-1601752327121-*#parkour00000000000000000000recordsFlash01#1465"},{"name":"brsowl#0000","time":4070,"link":"#parkour-1601663855259-*#parkour0records Brsowl#0000"},{"name":"andrew678#0000","time":4254,"link":"#parkour-1601663272374-es-#parkour999999999999recordsUlovemea#0000"},{"name":"syntia#9053","time":4502,"link":"#parkour-1601658952461-*#parkour1records Syntia#9053"}],"category":"parkour","img":"https://imgur.com/ra50zHx.png","recordsReversed":[]}