{"records":[{"name":"canibelles#0000","time":4399,"link":"#parkour-1601910771224-en-#parkour0records Canibelles#0000"},{"name":"arindy#9526","time":4440,"link":"#parkour-1601834630647-*#parkour0records Arindy#9526"},{"name":"brsowl#0000","time":4468,"link":"#parkour-1601914032043-*#parkour1records Missas#7766"},{"name":"kamal#8011","time":4611,"link":"#parkour-1601670511401-ar-#parkour00records-Kamal#8011"},{"name":"gmctf#0000","time":4691,"link":"#parkour-1601836790022-*#parkour1records Brsowl#0000"},{"name":"pikachusde#0000","time":4792,"link":"#parkour-1601657714819-*#parkour0records Syntia#9053"},{"name":"chuurippu#5010","time":4817,"link":"#parkour-1601818377113-tr-#parkour0records Chuurippu#5010"}],"category":"parkour","img":"https://imgur.com/xb5j9Ap.png","recordsReversed":[{"name":"ejsner#8749","time":3967,"link":"#parkour-*#parkour0records0Ejsner#8749","breaktime":1646638674918},{"name":"canibelles#0000","time":4037,"link":"#parkour-en-#parkour44records Canibelles#0000","breaktime":1624207428143},{"name":"mquk#0095","time":4173,"link":"#parkour-*#parkour5records Mquk#0095","timestamp":"2020-12-14T18:07:05.490Z"},{"name":"bitstev#0000","time":4220,"link":"#parkour-*#parkour0records Bitstev#0000","timestamp":"2020-11-27T07:38:41.015Z"},{"name":"ryurico#0000","time":4261,"link":"#parkour-*#parkour00records Ryurico#0000","timestamp":"2020-12-08T01:01:49.837Z"},{"name":"elmattjuan#0000","time":4293,"link":"#parkour-*#parkour0records0Elmattjuan#0000","timestamp":"2020-11-04T23:40:42.031Z"},{"name":"illusionize#9656","time":4366,"link":"#parkour-br-#parkour0records Illusionize#9656","timestamp":"2020-12-09T17:32:41.498Z"},{"name":"eltr#9580","time":5029,"link":"#parkour-es-#parkour0records Eltr#9580","timestamp":"2020-11-08T02:27:05.851Z"}],"author":"Erayaltun1#7987"}