{"records":[],"category":"parkour","img":"https://imgur.com/xqVhTLG.png","recordsReversed":[{"name":"eusounub#3461","time":1513,"link":"#parkour-*#parkour 0 records Eusounub#3461","breaktime":1652886570762},{"name":"itachi#9194","time":7268,"link":"#parkour-tr-#parkour06records Itachi#9194","breaktime":1651516155775},{"name":"nyucry#5903","time":7536,"link":"#parkour-*#parkour0recordsNyucry#5903","breaktime":1627246686091},{"name":"needfrox#0000","time":7586,"link":"#parkour-es-#parkour0records needfrox#0000","breaktime":1625709644359},{"name":"flooho#2180","time":7662,"link":"#parkour-*#parkour0records Bafffbotffah#0000","timestamp":"2021-02-27T03:45:00.180Z"},{"name":"acoolname#4878","time":8268,"link":"#parkour-es-#parkour0records Acoolname#4878","timestamp":"2020-11-25T00:54:01.707Z"},{"name":"krawk#5362","time":8580,"link":"#parkour-*#parkour0records Krawk#5362","timestamp":"2021-01-19T21:36:55.528Z"},{"name":"bafffbotffah#0000","time":9404,"link":"#parkour-*#parkour0records Bafffbotffah#0000","timestamp":"2021-02-28T05:11:24.674Z"},{"name":"emomouserat#0000","time":15718,"link":"#parkour-en-#parkour0records Emomouserat#0000","timestamp":"2020-12-15T20:11:59.078Z"}],"author":"Katmok#0000"}