{"records":[],"category":"parkour","img":"https://imgur.com/mUVDJhD.png","recordsReversed":[{"name":"vincentfarm#0000","time":8695,"link":"#parkour-*#parkour0recordsVincentfarm#0000","timestamp":"2020-12-18T15:40:24.803Z"},{"name":"yehitsme#0000","time":8778,"link":"#parkour-*#parkour0recordsVincentfarm#0000","timestamp":"2020-12-18T15:33:47.197Z"},{"name":"erizo#8425","time":10540,"link":"#parkour-*#parkour0records Erizo#8425","timestamp":"2020-12-15T21:31:30.158Z"},{"name":"supremorey#0000","time":11796,"link":"#parkour-*#parkour0records Supremorey#0000","timestamp":"2020-12-16T01:26:16.455Z"},{"name":"xmeneax#0000","time":16421,"link":"#parkour-*#parkour0records Supremorey#0000","timestamp":"2020-12-16T01:23:33.628Z"}]}