{"records":[{"name":"kaanov#9473","time":5284,"link":"#parkour-*#parkour0records slotmachines#0000","timestamp":"2021-01-05T03:57:38.324Z"},{"name":"markoneytor#6890","time":5379,"link":"#parkour-1602005884534-*#parkour8records Markoneytor#6890"},{"name":"krychassl#0000","time":5422,"link":"#parkour-1601992366873-pl-#parkour3records Abciokapcio#2843"},{"name":"gorylxl#4596","time":5603,"link":"#parkour-1601992234091-pl-#parkour3records Abciokapcio#2843"},{"name":"abciokapcio#2843","time":6113,"link":"#parkour-1601991589841-pl-#parkour3records Abciokapcio#2843"}],"category":"parkour","img":"https://imgur.com/bQgavTW.png","recordsReversed":[{"name":"nyucry#5903","time":4848,"link":"#parkour-sv-#parkour0recordsNyucry#5903","breaktime":1646415999300},{"name":"krychassl#0000","time":5008,"link":"#parkour-*#parkour0records Krychassl#0000","timestamp":"2021-03-14T18:38:26.235Z"},{"name":"kaanov#9473","time":5026,"link":"#parkour-*#parkour0records slotmachines#0000","timestamp":"2021-01-05T03:46:33.061Z"},{"name":"pequena12#9045","time":5431,"link":"#parkour-*#parkour0records Pequena12#9045","breaktime":1650068861864},{"name":"ahmeth#1934","time":5700,"link":"#parkour-*#parkour0records Ahmeth#1934","timestamp":"2021-03-31T16:56:34.157Z"},{"name":"bafffbotffah#0000","time":5788,"link":"#parkour-*#parkour0recordsBafffbotffah#0000","breaktime":1629937417820},{"name":"swagziin#4426","time":6753,"link":"#parkour-br-#parkour0recordsswagziin#4426","breaktime":1625713390413},{"name":"larifelton#0000","time":7271,"link":"#parkour-br-#parkour0recordsswagziin#4426","breaktime":1625713155538}]}