{"records":[{"name":"chil#0000","time":4896,"link":"#parkour-1602446707681-*#parkour0records Chil#0000"},{"name":"ahmedmice6#0000","time":5294,"link":"#parkour-1601593379358-ar-#parkour01records-Kamal#8011"},{"name":"flash01#1465","time":5499,"link":"#parkour-1601589683133-*#parkour0recordsFlash01#1465"},{"name":"acoolname#4878","time":5580,"link":"#parkour-1602626617415-*#parkour5records Acoolname#4878"}],"category":"parkour","img":"https://imgur.com/QtYF0vY.png","recordsReversed":[{"name":"thefourthone#0000","time":4828,"link":"*#parkour4records Thefourthone#0000"}]}