{"records":[{"name":"canibelles#0000","time":7073,"link":"#parkour-fr-#parkour4records Canibelles#0000","timestamp":"2020-10-23T12:20:26.019Z"},{"name":"sharpmuffinz#0000","time":7207,"link":"#parkour-*#parkour420speedypaws records Sharpmuffinz#0000","timestamp":"2020-10-23T00:20:57.759Z"},{"name":"vaaleehlocka#0000","time":11544,"link":"#parkour-*#parkour0speedypawandco records Sharpmuffinz#0000","timestamp":"2020-10-16T00:36:38.940Z"},{"name":"sakuraj#0000","time":13928,"link":"#parkour-1602361976617-*#parkour69speedypaws records Sharpmuffinz#0000"}],"category":"parkour","img":"https://imgur.com/C5C11ZT.png","recordsReversed":[]}