{"records":[{"name":"slotmachines#0000","time":4041,"link":"#parkour-*#parkour0records Slotmachines#0000","timestamp":"2020-10-30T01:56:42.136Z"},{"name":"gazdk#0000","time":4084,"link":"#parkour-1601647760452-*#parkour0recordsUlovemea#0000"},{"name":"hechizado#1243","time":4408,"link":"#parkour-1601618337074-lv-#parkour0records Hechizado#1243"},{"name":"brsowl#0000","time":4434,"link":"#parkour-1601606420037-br-#parkour0records Brsowl#0000"},{"name":"kamal#8011","time":4452,"link":"#parkour-1601591488520-ar-#parkour01records-Kamal#8011"},{"name":"pikachusde#0000","time":4885,"link":"#parkour-1601611094280-es-#parkour0recordsPikachusde#0000"}],"category":"parkour","img":"https://imgur.com/jfPPIEU.png","recordsReversed":[{"name":"ryurico#0000","time":4200,"link":"*#parkour0records Ryurico#0000"}]}